keysightosc/__init__.py
keysightosc/oscilloscope.py
keysightosc-0.1.2.dist-info/AUTHORS.rst
keysightosc-0.1.2.dist-info/LICENSE
keysightosc-0.1.2.dist-info/METADATA
keysightosc-0.1.2.dist-info/WHEEL
keysightosc-0.1.2.dist-info/top_level.txt
keysightosc-0.1.2.dist-info/RECORD
