Metadata-Version: 2.1
Name: keysightosc
Version: 0.1.2
Summary: Interface for Keysight Oscilloscopes.
Home-page: https://emt.uni-paderborn.de/
Author: Leander Claes
Author-email: claes@emt.uni-paderborn.de
License: BSD
Classifier: Development Status :: 2 - Pre-Alpha
Classifier: Intended Audience :: Science/Research
Classifier: License :: Other/Proprietary License
Classifier: Programming Language :: Python :: 3
Classifier: Topic :: Scientific/Engineering
Requires-Python: >=3
License-File: LICENSE
License-File: AUTHORS.rst
Requires-Dist: pyvisa
Requires-Dist: numpy
Requires-Dist: pyvisa-py ; sys_platform == "linux"
Requires-Dist: pyusb ; sys_platform == "linux"
